economynlp/__init__.py
economynlp/trading.py
economynlp/abnormal/__init__.py
economynlp/abnormal/bubble.py
economynlp/abnormal/over_reaction.py
economynlp/abnormal/winner_curse.py
economynlp/belief/__init__.py
economynlp/belief/belief_distortions.py
economynlp/belief/rational_beliefs.py
economynlp/belief/rational_expectations.py
economynlp/cognitive/__init__.py
economynlp/cognitive/confidence.py
economynlp/cognitive/metaphor/__init__.py
economynlp/cognitive/metaphor/black_swan.py
economynlp/cognitive/metaphor/grey_rhino.py
economynlp/cognitive/metaphor/herd_behavior.py
economynlp/cognitive/metaphor/invisible_hand.py
economynlp/cognitive/metaphor/putting_all_your_eggs_in_one_basket.py
economynlp/cognitive/metaphor/revolving_door.py
economynlp/cognitive/metaphor/tunneling.py
economynlp/cognitive/metaphor/visible_hand.py
economynlp/cognitive/metaphor/winner_takes_all.py
economynlp/culture/__init__.py
economynlp/culture/business_philosophy.py
economynlp/culture/mercantilism.py
economynlp/culture/spirit/__init__.py
economynlp/culture/spirit/craftsmanship.py
economynlp/culture/spirit/entrepreneurship.py
economynlp/culture/spirit/spirit.py
economynlp/decentralized_finance/DeFi.py
economynlp/decentralized_finance/__init__.py
economynlp/decorator/__init__.py
economynlp/decorator/announce.py
economynlp/decorator/audited.py
economynlp/decorator/economic_consequences.py
economynlp/decorator/endogenous.py
economynlp/decorator/estimate.py
economynlp/decorator/futuretense.py
economynlp/decorator/heterogeneous.py
economynlp/decorator/importance.py
economynlp/decorator/secret.py
economynlp/decorator/self_fulfilling.py
economynlp/decorator/spillover_effect.py
economynlp/decorator/validator.py
economynlp/decorator/welfare_effects.py
economynlp/decorator/witheffects.py
economynlp/environment/__init__.py
economynlp/environment/credit_environment.py
economynlp/environment/environment.py
economynlp/environment/industry_environment.py
economynlp/environment/market_environment.py
economynlp-0.0.18.dist-info/LICENSE
economynlp-0.0.18.dist-info/METADATA
economynlp-0.0.18.dist-info/WHEEL
economynlp-0.0.18.dist-info/top_level.txt
economynlp-0.0.18.dist-info/RECORD
