Metadata-Version: 2.1
Name: economynlp
Version: 0.0.18
Summary: Communicate in Economy with python
Home-page: https://economynlp.com
Author: Draco Deng
Author-email: dracodeng6@gmail.com
License: MIT
Keywords: python,economy,intelligent economy,linguistic turn,linguistic
Classifier: Intended Audience :: Developers
Classifier: License :: OSI Approved :: MIT License
Classifier: Programming Language :: Python :: 3
Classifier: Operating System :: Unix
Classifier: Operating System :: MacOS :: MacOS X
Classifier: Operating System :: Microsoft :: Windows
Classifier: Natural Language :: English
License-File: LICENSE
